lark_sqlpp/__init__.py
lark_sqlpp/collection_extractor.py
lark_sqlpp/ddl_checker.py
lark_sqlpp/dml_checker.py
lark_sqlpp/sqlpp.lark
lark_sqlpp-0.0.1.dist-info/METADATA
lark_sqlpp-0.0.1.dist-info/WHEEL
lark_sqlpp-0.0.1.dist-info/RECORD
