Metadata-Version: 2.4
Name: lark_sqlpp
Version: 0.0.1
Summary: A package containing lark grammar and parser method for sqlpp
Project-URL: Homepage, https://github.com/couchbaselabs/sqlpp-lark
Project-URL: Issues, https://github.com/couchbaselabs/sqlpp-lark/issues
Author-email: Dmitrii Chechetkin <dmitrii.chechetkin@couchbase.com>
Classifier: Development Status :: 4 - Beta
Classifier: Operating System :: OS Independent
Classifier: Programming Language :: Python :: 3
Requires-Python: >=3.9
Requires-Dist: lark>=1.2.2
